{
  "Universidad": {
    "nombre": "Universidad Autonoma de Nuevo Leon",
    "Facultades": [
      {
        "nombre": "Facultad de Ingenieria Mecanica y Electrica",
        "abrev": "FIME",
        "descripcion": "La Facultad de Ingeniería Mecánica y Eléctrica (FIME) es una Institución educativa de nivel superior y pertenece a la Universidad Autónoma de Nuevo León.",
        "coordenadas": "25.72536, -100.31346",
        "marcador": [
          {
            "nombre": "Cafeteria FIME",
            "descripcion": "La cafeteria oficial de FIME.",
            "categoria": "Comidas",
            "coordenadas": "25.72565, -100.31373",
            "tags": "comidas, cafeteria, burritos, pollo, refrescos, agua, coca, soda, desayuno, carne, mesas, servilletas",
            "icon": "utensils"
          },
          {
            "nombre": "Papeleria FIME",
            "descripcion": "Venta de utensilios escolares universitarios.",
            "categoria": "Papeleria",
            "coordenadas": "25.72549, -100.31343",
            "tags": "copias, papeleria, utensilios, enmicado, engargolado, impresiones",
            "icon": "paperclip"
          },
          {
            "nombre": "Bebedero ",
            "descripcion": "Bebedero del edificio 4 de FIME, cuenta con refill de agua.",
            "categoria": "Bebederos",
            "coordenadas": "25.72635,-100.31344",
            "tags": "agua, refill, bebederos",
            "icon": "tint"
          },
          {
            "nombre": "Bebedero",
            "descripcion": "Bebedero detras del edificio 4 de FIME, cuenta con refill de agua.",
            "categoria": "Bebederos",
            "coordenadas": "25.72616,-100.31305",
            "tags": "agua, refill, bebederos",
            "icon": "tint"
          },
          {
            "nombre": "Bebedero",
            "descripcion": "Bebedero a lado del edificio 3 de FIME.",
            "categoria": "Bebederos",
            "coordenadas": "25.72595,-100.31334",
            "tags": "agua, bebedero, bebederos",
            "icon": "tint"
          },
          {
            "nombre": "Baño",
            "descripcion": "Baños dentro del edificio 4 de FIME.",
            "categoria": "Baños",
            "coordenadas": "25.72624,-100.31316",
            "tags": "lavabos, jabon, baños",
            "icon": "restroom"
          },
          {
            "nombre": "Baño",
            "descripcion": "Dos baños dentro de la biblioteca de FIME, primer y tercer piso.",
            "categoria": "Baños",
            "coordenadas": "25.72622,-100.31377",
            "tags": "lavabos, jabon, baños",
            "icon": "restroom"
          },
          {
            "nombre": "Baño",
            "descripcion": "Baños dentro del edificio 6 de FIME en el segundo piso.",
            "categoria": "Baños",
            "coordenadas": "25.72597,-100.31392",
            "tags": "lavabos, jabon, baños",
            "icon": "restroom"
          },
          {
            "nombre": "Baño",
            "descripcion": "Baños en el edificio 1 de FIME, primer piso para hombres, segundo piso para mujeres.",
            "categoria": "Baños",
            "coordenadas": "25.72524,-100.31333",
            "tags": "lavabos, jabon, baños",
            "icon": "restroom"
          },
          {
            "nombre": "Baño",
            "descripcion": "Baños en el edificio 2 de FIME, primer piso de hombres, segundo piso para mujeres.",
            "categoria": "Baños",
            "coordenadas": "25.72524,-100.31333",
            "tags": "lavabos, jabon, baños",
            "icon": "restroom"
          },
          {
            "nombre": "Baño",
            "descripcion": "Baños en el edificio 3 de FIME, primer piso de hombres (entrada por HUBNATURA), segundo piso para mujeres, tercer piso para hombres.",
            "categoria": "Baños",
            "coordenadas": "25.72600,-100.31328",
            "tags": "lavabos, jabon, baños",
            "icon": "restroom"
          },
          {
            "nombre": "Baño",
            "descripcion": "Baños en el edificio 9 de FIME, segundo piso de mujeres, tercer piso para hombres.",
            "categoria": "Baños",
            "coordenadas": "25.72600,-100.31328",
            "tags": "lavabos, jabon, baños",
            "icon": "restroom"
          }
        ]
      },
      {
        "nombre": "Facultad de Arquitectura",
        "abrev": "FARQ",
        "descripcion": "La Facultad de Ingeniería Mecánica y Eléctrica (FIME) es una Institución educativa de nivel superior y pertenece a la Universidad Autónoma de Nuevo León.",
        "coordenadas": "25.72516, -100.31200",
        "marcador": [
          {
            "nombre": "Cafeteria FARQ",
            "descripcion": "La cafeteria oficial de FARQ.",
            "categoria": "Comidas",
            "coordenadas": "25.72544, -100.31118",
            "tags": "comidas, cafeteria, burritos, pollo, refrescos, agua, coca, soda, desayuno, carne, mesas, servilletas",
            "icon": "utensils"
          },
          {
            "nombre": "Papeleria FARQ",
            "descripcion": "Venta de utensilios escolares universitarios.",
            "categoria": "Papeleria",
            "coordenadas": "25.72564, -100.31193",
            "tags": "copias, papeleria, utensilios, enmicado, engargolado, impresiones",
            "icon": "paperclip"
          }
        ]
      },
      {
        "nombre": "Facultad de Contaduría Pública y Administración",
        "abrev": "FACPYA",
        "descripcion": "La Facultad de Contaduría Pública y Administración (FACPYA) es una Institución educativa de nivel superior y pertenece a la Universidad Autónoma de Nuevo León.",
        "coordenadas": "25.72728, -100.30913",
        "marcador": [
          {
            "nombre": "Cafeteria FACPYA",
            "descripcion": "La cafeteria oficial de FACPYA.",
            "categoria": "Comidas",
            "coordenadas": "25.72761,-100.30954",
            "horario": "7:00 AM - 9:30 PM",
            "tags": "comidas, cafeteria, burritos, pollo, refrescos, agua, coca, soda, desayuno, carne, mesas, servilletas",
            "icon": "utensils"
          },
          {
            "nombre": "Biblioteca de FACPYA",
            "descripcion": "Biblioteca FACPYA",
            "categoria": "Biblioteca",
            "coordenadas": "25.72734,-100.30938",
            "tags": "libros, estudio, descanso, computadoras, cubiculos",
            "icon": "book-reader"
          },
          {
            "nombre": "Hotchos de FACPYA",
            "descripcion": "Establecimiento de hot dogs ubicado a un costado de la cafetería de FACPYA.",
            "categoria": "Comidas",
            "coordenadas": "25.72749,-100.30946",
            "horario": "8:30 AM - 9:30 PM",
            "precios": "Hotdogs grandes $20, Hotdogs normales $15",
            "tags": "hotdogs, hotchos, comidas",
            "icon": "hotdog"
          },
          {
            "nombre": "Snack de FACPYA",
            "descripcion": "Snack ubicado entre FACPYA y Trabajo Social ",
            "categoria": "Comidas",
            "coordenadas": "25.72812,-100.30970",
            "horario": "8:00 AM - 9:30 PM",
            "tags": "snacks, comidas, refrescos, coca, soda, papas",
            "icon": "hamburger"
          },
          {
            "nombre": "Papeleria FACPYA",
            "descripcion": "Centro de copiado e impresion a un costado de la Biblioteca de FACPYA",
            "categoria": "Papeleria",
            "coordenadas": "25.72733,-100.30952",
            "horario": "7:00 AM - 9:00 PM",
            "tags": "copias, papeleria, utensilios, enmicado, engargolado, impresiones",
            "icon": "paperclip"
          },
          {
            "nombre": "Articulos FACPYA Libreria Elefantes",
            "descripcion": "Venta de souvenirs",
            "categoria": "Ventas",
            "coordenadas": "25.72730,-100.30954",
            "horario": "10:00 AM - 8:30 PM",
            "precios": "Impresion B&N $1.00 c/u, copias $0.50 c/u.",
            "tags": "souvenirs, articulos, elefantes, tienda, chaquetas, paraguas, termos, mochilas, maletines",
            "icon": "gifts"
          },
          {
            "nombre": "Baños",
            "descripcion": "Baños ubicados en el Edificio 11, hombres primer piso/mujeres segundo piso.",
            "categoria": "Baños",
            "coordenadas": "25.72862,-100.30877",
            "tags": "lavabos, jabon, baños",
            "icon": "restroom"
          },
          {
            "nombre": "Baños",
            "descripcion": "Baños ubicados en el Edificio 8.",
            "categoria": "Baños",
            "coordenadas": "25.72807,-100.30914",
            "tags": "lavabos, jabon, baños",
            "icon": "restroom"
          },
          {
            "nombre": "Baños",
            "descripcion": "Baños ubicados en el Edificio 1.",
            "categoria": "Baños",
            "coordenadas": "25.72741,-100.30961",
            "tags": "lavabos, jabon, baños",
            "icon": "restroom"
          },
          {
            "nombre": "Bebedero",
            "descripcion": "Bebedero ubicado en el area central de FACPYA",
            "categoria": "Bebederos",
            "coordenadas": "25.72808,-100.30927",
            "tags": "agua, bebedero, bebederos",
            "icon": "tint"
          },
          {
            "nombre": "Bebedero",
            "descripcion": "Bebedero ubicado frente a la Biblioteca de FACPYA, cuenta con refill",
            "categoria": "Bebederos",
            "coordenadas": "25.72744,-100.30930",
            "tags": "agua, bebedero, bebederos",
            "icon": "tint"
          }
        ]
      }
    ]
  }
}